odoo/addons/energy_communities_crm/__init__.py
odoo/addons/energy_communities_crm/__manifest__.py
odoo/addons/energy_communities_crm/controllers/__init__.py
odoo/addons/energy_communities_crm/controllers/website_community_data.py
odoo/addons/energy_communities_crm/data/crm_lead_tag.xml
odoo/addons/energy_communities_crm/data/mail_template_data.xml
odoo/addons/energy_communities_crm/data/res_users_role_data.xml
odoo/addons/energy_communities_crm/i18n/ca_ES.po
odoo/addons/energy_communities_crm/i18n/es.po
odoo/addons/energy_communities_crm/i18n/eu_ES.po
odoo/addons/energy_communities_crm/models/__init__.py
odoo/addons/energy_communities_crm/models/crm_lead.py
odoo/addons/energy_communities_crm/models/crm_lead_metadata_line.py
odoo/addons/energy_communities_crm/models/crm_lead_metadata_mapping.py
odoo/addons/energy_communities_crm/models/crm_lead_metadata_mapping_field.py
odoo/addons/energy_communities_crm/models/crm_stage.py
odoo/addons/energy_communities_crm/models/crm_tag.py
odoo/addons/energy_communities_crm/models/crm_team.py
odoo/addons/energy_communities_crm/models/metadata_mapping_conf.py
odoo/addons/energy_communities_crm/models/utm_source.py
odoo/addons/energy_communities_crm/security/ir.model.access.csv
odoo/addons/energy_communities_crm/security/ir_rule_data.xml
odoo/addons/energy_communities_crm/security/res_users_role_data.xml
odoo/addons/energy_communities_crm/services/__init__.py
odoo/addons/energy_communities_crm/services/crm_lead_service.py
odoo/addons/energy_communities_crm/static/src/js/community-data-website.js
odoo/addons/energy_communities_crm/tests/__init__.py
odoo/addons/energy_communities_crm/tests/test_crm_lead.py
odoo/addons/energy_communities_crm/tests/test_crm_lead_service.py
odoo/addons/energy_communities_crm/views/crm_lead_metadata_mapping_views.xml
odoo/addons/energy_communities_crm/views/crm_lead_views.xml
odoo/addons/energy_communities_crm/views/crm_stage_views.xml
odoo/addons/energy_communities_crm/views/crm_tag_views.xml
odoo14_addon_energy_communities_crm-14.0.1.3.0.dist-info/METADATA
odoo14_addon_energy_communities_crm-14.0.1.3.0.dist-info/WHEEL
odoo14_addon_energy_communities_crm-14.0.1.3.0.dist-info/top_level.txt
odoo14_addon_energy_communities_crm-14.0.1.3.0.dist-info/RECORD
