Metadata-Version: 2.1
Name: odoo14-addon-energy-communities-crm
Version: 14.0.1.3.0
Summary: Use CRM for coordinators and energy communities
Home-page: https://coopdevs.org
Author: Som Comunitats
License: AGPL-3
Classifier: Programming Language :: Python
Classifier: Framework :: Odoo
Classifier: Framework :: Odoo :: 14.0
Classifier: License :: OSI Approved :: GNU Affero General Public License v3
Requires-Python: >=3.6
Requires-Dist: odoo14-addon-crm-metadata-rest-api ==14.0.1.0.2
Requires-Dist: odoo14-addon-crm-metadata ==14.0.1.0.0
Requires-Dist: odoo14-addon-crm-rest-api ==14.0.1.0.2
Requires-Dist: odoo14-addon-energy-communities >=14.0.9.0.0
Requires-Dist: odoo <14.1dev,>=14.0a
